README.md
setup.py
nace/__init__.py
nace/actions_module.py
nace/agent_module.py
nace/color_codes.py
nace/graph_utilities.py
nace/gymnasium_action_decoder.py
nace/hypothesis.py
nace/hypothesis_tests.py
nace/key_utils.py
nace/nace_v3.py
nace/nace_v3_build_change_set_tests.py
nace/nace_v3_observe_tests.py
nace/nacev3_plan_tests.py
nace/nacev3_predict_tests.py
nace/nacev3_predict_tests_inprogress.py
nace/numpy_util_tests.py
nace/numpy_utils.py
nace/prettyprint.py
nace/prettyprint_tests.py
nace/rule_evidence_utils.py
nace/stepper_v4.py
nace/test_utilities.py
nace/world_module.py
nace/world_module_numpy.py
nace/world_module_numpy_tests.py
nace/world_module_numpy_tests_old.py
nace.egg-info/PKG-INFO
nace.egg-info/SOURCES.txt
nace.egg-info/dependency_links.txt
nace.egg-info/requires.txt
nace.egg-info/top_level.txt
tests/__init__.py
tests/context.py
tests/nace_v3_observe_tests.py