Metadata-Version: 2.1
Name: nace
Version: 0.0.29
Summary: A re-implementation of NACE, as a pypi package, with a cleaner more general interface.
Author: ucabdv1
Author-email: ucabdv1@ucl.ac.uk
Classifier: Programming Language :: Python :: 3
Classifier: License :: OSI Approved :: MIT License
Classifier: Operating System :: OS Independent
Requires-Python: >=3.9
Requires-Dist: numba>=0.60.0
Requires-Dist: gymnasium
Requires-Dist: numba
Requires-Dist: pygame
Requires-Dist: xxhash==3.5.0
Requires-Dist: opencv-python
Requires-Dist: bidict
Requires-Dist: matplotlib
Requires-Dist: getch
